pykeycontrol/README.MD
pykeycontrol/__init__.py
pykeycontrol/requirements.txt
pykeycontrol/thirdparty.json
pykeycontrol-0.10.dist-info/LICENSE.rst
pykeycontrol-0.10.dist-info/METADATA
pykeycontrol-0.10.dist-info/WHEEL
pykeycontrol-0.10.dist-info/top_level.txt
pykeycontrol-0.10.dist-info/RECORD
